{"cameraMode":{"drawMode":0,"name":"Shaded","section":"Shading Mode"},"sceneLighting":false,"audioPlay":false,"sceneViewState":{"showFog":true,"showMaterialUpdate":false,"showSkybox":false,"showFlares":true,"showImageEffects":true,"showParticleSystems":true},"in2DMode":false,"pivot":{"x":0.5134046077728272,"y":0.9434927701950073,"z":-0.20312342047691346},"rotation":{"x":-0.32007405161857607,"y":-0.0039823963306844238,"z":-0.0013357715215533972,"w":0.9474192261695862},"size":3.3674850463867189,"orthographic":false}